{
    "nodes": [{
        "name": "Alderwood High School",
        "counter": 51,
        "rank": 0,
        "frequency": 91,
        "type": "Organization",
        "id": 0
    }, {
        "name": "Grizzlies",
        "counter": 31,
        "rank": 0,
        "frequency": 856,
        "type": "Organization",
        "id": 1
    }, {
        "name": "Yakima County",
        "counter": 21,
        "rank": 0,
        "frequency": 259,
        "type": "Location",
        "id": 2
    }, {
        "name": "WASL",
        "counter": 18,
        "rank": 0,
        "frequency": 348,
        "type": "Organization",
        "id": 3
    }, {
        "name": "Washington",
        "counter": 91,
        "rank": 0,
        "frequency": 117,
        "type": "Location",
        "id": 4
    }, {
        "name": "Marro",
        "counter": 25,
        "rank": 0,
        "frequency": 1576,
        "type": "Person",
        "id": 5
    }, {
        "name": "Prosser",
        "counter": 22,
        "rank": 0,
        "frequency": 246,
        "type": "Person",
        "id": 6
    }, {
        "name": "Albert Smith",
        "counter": 27,
        "rank": 0,
        "frequency": 568,
        "type": "Person",
        "id": 7
    }, {
        "name": "Kerry",
        "counter": 31,
        "rank": 0,
        "frequency": 850,
        "type": "Person",
        "id": 8
    }, {
        "name": "Alderwood Community Hospital",
        "counter": 19,
        "rank": 0,
        "frequency": 130,
        "type": "Organization",
        "id": 9
    }, {
        "name": "Alderwood School District",
        "counter": 34,
        "rank": 0,
        "frequency": 149,
        "type": "Organization",
        "id": 10
    }, {
        "name": "Mel Sacher",
        "counter": 21,
        "rank": 0,
        "frequency": 109,
        "type": "Person",
        "id": 11
    }, {
        "name": "John Panni Date",
        "counter": 24,
        "rank": 0,
        "frequency": 0,
        "type": "Person",
        "id": 12
    }, {
        "name": "Hastings",
        "counter": 27,
        "rank": 0,
        "frequency": 2065,
        "type": "Person",
        "id": 13
    }, {
        "name": "Martinez",
        "counter": 29,
        "rank": 0,
        "frequency": 371,
        "type": "Person",
        "id": 14
    }, {
        "name": "Seattle",
        "counter": 34,
        "rank": 0,
        "frequency": 118,
        "type": "Location",
        "id": 15
    }, {
        "name": "Alderwood City Council",
        "counter": 36,
        "rank": 0,
        "frequency": 302,
        "type": "Organization",
        "id": 16
    }, {
        "name": "Yakima",
        "counter": 56,
        "rank": 0,
        "frequency": 134,
        "type": "Location",
        "id": 17
    }, {
        "name": "Alderwood School Board",
        "counter": 23,
        "rank": 0,
        "frequency": 349,
        "type": "Organization",
        "id": 18
    }, {
        "name": "Mabton",
        "counter": 54,
        "rank": 0,
        "frequency": 374,
        "type": "Location",
        "id": 19
    }, {
        "name": "LaFever",
        "counter": 31,
        "rank": 0,
        "frequency": 1325,
        "type": "Person",
        "id": 20
    }, {
        "name": "Yakima Valley",
        "counter": 18,
        "rank": 0,
        "frequency": 99,
        "type": "Location",
        "id": 21
    }, {
        "name": "Pineda",
        "counter": 19,
        "rank": 0,
        "frequency": 1924,
        "type": "Person",
        "id": 22
    }, {
        "name": "Bush",
        "counter": 20,
        "rank": 0,
        "frequency": 458,
        "type": "Person",
        "id": 23
    }, {
        "name": "Alderwood Weekly Lucky Numbers Story",
        "counter": 27,
        "rank": 0,
        "frequency": 0,
        "type": "Organization",
        "id": 24
    }, {
        "name": "James",
        "counter": 27,
        "rank": 0,
        "frequency": 913,
        "type": "Person",
        "id": 25
    }, {
        "name": "United States",
        "counter": 27,
        "rank": 0,
        "frequency": 167,
        "type": "Location",
        "id": 26
    }, {
        "name": "Nethercutt",
        "counter": 25,
        "rank": 0,
        "frequency": 1502,
        "type": "Person",
        "id": 27
    }, {
        "name": "Wells Funeral Home",
        "counter": 51,
        "rank": 0,
        "frequency": 310,
        "type": "Organization",
        "id": 28
    }, {
        "name": "Schuette",
        "counter": 19,
        "rank": 0,
        "frequency": 2603,
        "type": "Person",
        "id": 29
    }, {
        "name": "Pasillas",
        "counter": 40,
        "rank": 0,
        "frequency": 3690,
        "type": "Person",
        "id": 30
    }, {
        "name": "Alderwood",
        "counter": 366,
        "rank": 0,
        "frequency": 63,
        "type": "Location",
        "id": 31
    }, {
        "name": "Council",
        "counter": 50,
        "rank": 0,
        "frequency": 597,
        "type": "Organization",
        "id": 32
    }, {
        "name": "Jamie Smart Date",
        "counter": 20,
        "rank": 0,
        "frequency": 0,
        "type": "Person",
        "id": 33
    }, {
        "name": "Rockford",
        "counter": 59,
        "rank": 0,
        "frequency": 653,
        "type": "Location",
        "id": 34
    }, {
        "name": "Alderwood",
        "counter": 126,
        "rank": 0,
        "frequency": 55,
        "type": "Organization",
        "id": 35
    }, {
        "name": "Grandview",
        "counter": 132,
        "rank": 0,
        "frequency": 314,
        "type": "Location",
        "id": 36
    }, {
        "name": "Alderwood County",
        "counter": 24,
        "rank": 0,
        "frequency": 326,
        "type": "Location",
        "id": 37
    }, {
        "name": "Ellie Olmsen Date",
        "counter": 30,
        "rank": 0,
        "frequency": 0,
        "type": "Person",
        "id": 38
    }, {
        "name": "Lower Valley",
        "counter": 22,
        "rank": 0,
        "frequency": 85,
        "type": "Location",
        "id": 39
    }, {
        "name": "Davis",
        "counter": 20,
        "rank": 0,
        "frequency": 1580,
        "type": "Person",
        "id": 40
    }],
    "links": [{
        "source": 16,
        "target": 9,
        "weight": 4
    }, {
        "source": 4,
        "target": 36,
        "weight": 1
    }, {
        "source": 19,
        "target": 4,
        "weight": 5
    }, {
        "source": 17,
        "target": 20,
        "weight": 4
    }, {
        "source": 36,
        "target": 34,
        "weight": 2
    }, {
        "source": 35,
        "target": 15,
        "weight": 1
    }, {
        "source": 38,
        "target": 40,
        "weight": 18
    }, {
        "source": 34,
        "target": 8,
        "weight": 24
    }, {
        "source": 11,
        "target": 22,
        "weight": 3
    }, {
        "source": 35,
        "target": 21,
        "weight": 1
    }, {
        "source": 0,
        "target": 17,
        "weight": 1
    }, {
        "source": 38,
        "target": 2,
        "weight": 1
    }, {
        "source": 19,
        "target": 39,
        "weight": 1
    }, {
        "source": 31,
        "target": 15,
        "weight": 1
    }, {
        "source": 16,
        "target": 0,
        "weight": 1
    }, {
        "source": 17,
        "target": 13,
        "weight": 5
    }, {
        "source": 31,
        "target": 21,
        "weight": 1
    }, {
        "source": 9,
        "target": 9,
        "weight": 1
    }, {
        "source": 10,
        "target": 14,
        "weight": 3
    }, {
        "source": 35,
        "target": 26,
        "weight": 1
    }, {
        "source": 12,
        "target": 8,
        "weight": 10
    }, {
        "source": 13,
        "target": 13,
        "weight": 1
    }, {
        "source": 26,
        "target": 23,
        "weight": 3
    }, {
        "source": 0,
        "target": 14,
        "weight": 16
    }, {
        "source": 4,
        "target": 12,
        "weight": 9
    }, {
        "source": 0,
        "target": 36,
        "weight": 1
    }, {
        "source": 6,
        "target": 14,
        "weight": 1
    }, {
        "source": 19,
        "target": 18,
        "weight": 1
    }, {
        "source": 31,
        "target": 18,
        "weight": 14
    }, {
        "source": 9,
        "target": 40,
        "weight": 3
    }, {
        "source": 34,
        "target": 32,
        "weight": 180
    }, {
        "source": 10,
        "target": 9,
        "weight": 3
    }, {
        "source": 11,
        "target": 4,
        "weight": 1
    }, {
        "source": 25,
        "target": 25,
        "weight": 1
    }, {
        "source": 15,
        "target": 10,
        "weight": 2
    }, {
        "source": 11,
        "target": 26,
        "weight": 1
    }, {
        "source": 0,
        "target": 5,
        "weight": 25
    }, {
        "source": 12,
        "target": 29,
        "weight": 18
    }, {
        "source": 39,
        "target": 23,
        "weight": 1
    }, {
        "source": 29,
        "target": 29,
        "weight": 1
    }, {
        "source": 4,
        "target": 17,
        "weight": 1
    }, {
        "source": 2,
        "target": 33,
        "weight": 1
    }, {
        "source": 26,
        "target": 34,
        "weight": 1
    }, {
        "source": 31,
        "target": 27,
        "weight": 31
    }, {
        "source": 17,
        "target": 17,
        "weight": 1
    }, {
        "source": 31,
        "target": 33,
        "weight": 23
    }, {
        "source": 11,
        "target": 39,
        "weight": 1
    }, {
        "source": 35,
        "target": 34,
        "weight": 1
    }, {
        "source": 12,
        "target": 32,
        "weight": 1
    }, {
        "source": 36,
        "target": 37,
        "weight": 1
    }, {
        "source": 13,
        "target": 37,
        "weight": 1
    }, {
        "source": 35,
        "target": 8,
        "weight": 13
    }, {
        "source": 11,
        "target": 19,
        "weight": 1
    }, {
        "source": 38,
        "target": 9,
        "weight": 1
    }, {
        "source": 15,
        "target": 39,
        "weight": 1
    }, {
        "source": 0,
        "target": 40,
        "weight": 1
    }, {
        "source": 31,
        "target": 0,
        "weight": 89
    }, {
        "source": 6,
        "target": 18,
        "weight": 1
    }, {
        "source": 17,
        "target": 10,
        "weight": 12
    }, {
        "source": 16,
        "target": 33,
        "weight": 1
    }, {
        "source": 36,
        "target": 10,
        "weight": 3
    }, {
        "source": 35,
        "target": 23,
        "weight": 7
    }, {
        "source": 38,
        "target": 0,
        "weight": 1
    }, {
        "source": 0,
        "target": 9,
        "weight": 1
    }, {
        "source": 38,
        "target": 26,
        "weight": 1
    }, {
        "source": 28,
        "target": 4,
        "weight": 1
    }, {
        "source": 31,
        "target": 9,
        "weight": 83
    }, {
        "source": 6,
        "target": 21,
        "weight": 1
    }, {
        "source": 19,
        "target": 15,
        "weight": 1
    }, {
        "source": 17,
        "target": 3,
        "weight": 4
    }, {
        "source": 32,
        "target": 37,
        "weight": 1
    }, {
        "source": 31,
        "target": 23,
        "weight": 15
    }, {
        "source": 33,
        "target": 32,
        "weight": 1
    }, {
        "source": 17,
        "target": 37,
        "weight": 3
    }, {
        "source": 10,
        "target": 12,
        "weight": 8
    }, {
        "source": 14,
        "target": 14,
        "weight": 1
    }, {
        "source": 15,
        "target": 15,
        "weight": 1
    }, {
        "source": 39,
        "target": 2,
        "weight": 2
    }, {
        "source": 26,
        "target": 21,
        "weight": 1
    }, {
        "source": 0,
        "target": 0,
        "weight": 1
    }, {
        "source": 4,
        "target": 14,
        "weight": 2
    }, {
        "source": 6,
        "target": 12,
        "weight": 1
    }, {
        "source": 18,
        "target": 3,
        "weight": 8
    }, {
        "source": 6,
        "target": 38,
        "weight": 1
    }, {
        "source": 35,
        "target": 5,
        "weight": 92
    }, {
        "source": 12,
        "target": 1,
        "weight": 1
    }, {
        "source": 38,
        "target": 20,
        "weight": 31
    }, {
        "source": 39,
        "target": 17,
        "weight": 1
    }, {
        "source": 28,
        "target": 26,
        "weight": 1
    }, {
        "source": 26,
        "target": 32,
        "weight": 5
    }, {
        "source": 31,
        "target": 5,
        "weight": 45
    }, {
        "source": 19,
        "target": 3,
        "weight": 4
    }, {
        "source": 35,
        "target": 36,
        "weight": 1
    }, {
        "source": 12,
        "target": 34,
        "weight": 1
    }, {
        "source": 36,
        "target": 39,
        "weight": 1
    }, {
        "source": 35,
        "target": 10,
        "weight": 3
    }, {
        "source": 33,
        "target": 14,
        "weight": 11
    }, {
        "source": 35,
        "target": 16,
        "weight": 1
    }, {
        "source": 0,
        "target": 30,
        "weight": 79
    }, {
        "source": 38,
        "target": 15,
        "weight": 1
    }, {
        "source": 12,
        "target": 22,
        "weight": 16
    }, {
        "source": 39,
        "target": 14,
        "weight": 11
    }, {
        "source": 28,
        "target": 17,
        "weight": 1
    }, {
        "source": 15,
        "target": 33,
        "weight": 2
    }, {
        "source": 4,
        "target": 26,
        "weight": 1
    }, {
        "source": 28,
        "target": 15,
        "weight": 1
    }, {
        "source": 31,
        "target": 2,
        "weight": 2
    }, {
        "source": 6,
        "target": 16,
        "weight": 1
    }, {
        "source": 4,
        "target": 32,
        "weight": 1
    }, {
        "source": 32,
        "target": 32,
        "weight": 1
    }, {
        "source": 31,
        "target": 40,
        "weight": 24
    }, {
        "source": 10,
        "target": 3,
        "weight": 5
    }, {
        "source": 15,
        "target": 26,
        "weight": 1
    }, {
        "source": 11,
        "target": 10,
        "weight": 1
    }, {
        "source": 0,
        "target": 21,
        "weight": 1
    }, {
        "source": 12,
        "target": 13,
        "weight": 5
    }, {
        "source": 36,
        "target": 18,
        "weight": 12
    }, {
        "source": 2,
        "target": 23,
        "weight": 2
    }, {
        "source": 26,
        "target": 8,
        "weight": 10
    }, {
        "source": 28,
        "target": 6,
        "weight": 56
    }, {
        "source": 0,
        "target": 33,
        "weight": 8
    }, {
        "source": 19,
        "target": 17,
        "weight": 12
    }, {
        "source": 31,
        "target": 17,
        "weight": 1
    }, {
        "source": 34,
        "target": 37,
        "weight": 15
    }, {
        "source": 17,
        "target": 27,
        "weight": 5
    }, {
        "source": 9,
        "target": 13,
        "weight": 1
    }, {
        "source": 38,
        "target": 39,
        "weight": 1
    }, {
        "source": 10,
        "target": 10,
        "weight": 1
    }, {
        "source": 11,
        "target": 3,
        "weight": 1
    }, {
        "source": 35,
        "target": 30,
        "weight": 86
    }, {
        "source": 15,
        "target": 9,
        "weight": 5
    }, {
        "source": 0,
        "target": 2,
        "weight": 1
    }, {
        "source": 39,
        "target": 26,
        "weight": 1
    }, {
        "source": 4,
        "target": 8,
        "weight": 38
    }, {
        "source": 31,
        "target": 30,
        "weight": 43
    }, {
        "source": 16,
        "target": 17,
        "weight": 1
    }, {
        "source": 6,
        "target": 36,
        "weight": 1
    }, {
        "source": 31,
        "target": 36,
        "weight": 1
    }, {
        "source": 35,
        "target": 33,
        "weight": 17
    }, {
        "source": 12,
        "target": 37,
        "weight": 1
    }, {
        "source": 26,
        "target": 26,
        "weight": 1
    }, {
        "source": 38,
        "target": 10,
        "weight": 1
    }, {
        "source": 28,
        "target": 36,
        "weight": 1
    }, {
        "source": 2,
        "target": 3,
        "weight": 8
    }, {
        "source": 19,
        "target": 31,
        "weight": 3
    }, {
        "source": 31,
        "target": 7,
        "weight": 13
    }, {
        "source": 6,
        "target": 31,
        "weight": 1
    }, {
        "source": 17,
        "target": 21,
        "weight": 1
    }, {
        "source": 35,
        "target": 38,
        "weight": 9
    }, {
        "source": 18,
        "target": 18,
        "weight": 1
    }, {
        "source": 23,
        "target": 27,
        "weight": 8
    }, {
        "source": 36,
        "target": 33,
        "weight": 1
    }, {
        "source": 35,
        "target": 12,
        "weight": 32
    }, {
        "source": 14,
        "target": 30,
        "weight": 1
    }, {
        "source": 23,
        "target": 23,
        "weight": 1
    }, {
        "source": 11,
        "target": 23,
        "weight": 1
    }, {
        "source": 35,
        "target": 18,
        "weight": 2
    }, {
        "source": 38,
        "target": 13,
        "weight": 20
    }, {
        "source": 36,
        "target": 21,
        "weight": 1
    }, {
        "source": 39,
        "target": 8,
        "weight": 12
    }, {
        "source": 28,
        "target": 19,
        "weight": 1
    }, {
        "source": 3,
        "target": 3,
        "weight": 1
    }, {
        "source": 4,
        "target": 4,
        "weight": 1
    }, {
        "source": 28,
        "target": 9,
        "weight": 1
    }, {
        "source": 31,
        "target": 12,
        "weight": 21
    }, {
        "source": 19,
        "target": 10,
        "weight": 18
    }, {
        "source": 17,
        "target": 14,
        "weight": 4
    }, {
        "source": 16,
        "target": 37,
        "weight": 1
    }, {
        "source": 0,
        "target": 23,
        "weight": 2
    }, {
        "source": 38,
        "target": 4,
        "weight": 1
    }, {
        "source": 1,
        "target": 22,
        "weight": 144
    }, {
        "source": 15,
        "target": 2,
        "weight": 2
    }, {
        "source": 0,
        "target": 13,
        "weight": 2
    }, {
        "source": 4,
        "target": 3,
        "weight": 38
    }, {
        "source": 28,
        "target": 0,
        "weight": 1
    }, {
        "source": 6,
        "target": 9,
        "weight": 1
    }, {
        "source": 19,
        "target": 19,
        "weight": 1
    }, {
        "source": 20,
        "target": 20,
        "weight": 1
    }, {
        "source": 6,
        "target": 35,
        "weight": 1
    }, {
        "source": 38,
        "target": 37,
        "weight": 1
    }, {
        "source": 10,
        "target": 8,
        "weight": 1
    }, {
        "source": 39,
        "target": 32,
        "weight": 13
    }, {
        "source": 35,
        "target": 0,
        "weight": 1
    }, {
        "source": 9,
        "target": 21,
        "weight": 1
    }, {
        "source": 10,
        "target": 18,
        "weight": 1
    }, {
        "source": 11,
        "target": 27,
        "weight": 20
    }, {
        "source": 38,
        "target": 17,
        "weight": 1
    }, {
        "source": 1,
        "target": 1,
        "weight": 1
    }, {
        "source": 4,
        "target": 10,
        "weight": 16
    }, {
        "source": 28,
        "target": 31,
        "weight": 1
    }, {
        "source": 6,
        "target": 0,
        "weight": 1
    }, {
        "source": 4,
        "target": 16,
        "weight": 5
    }, {
        "source": 26,
        "target": 37,
        "weight": 2
    }, {
        "source": 31,
        "target": 24,
        "weight": 13
    }, {
        "source": 6,
        "target": 26,
        "weight": 1
    }, {
        "source": 17,
        "target": 18,
        "weight": 7
    }, {
        "source": 31,
        "target": 38,
        "weight": 24
    }, {
        "source": 11,
        "target": 36,
        "weight": 1
    }, {
        "source": 35,
        "target": 35,
        "weight": 1
    }, {
        "source": 36,
        "target": 36,
        "weight": 1
    }, {
        "source": 35,
        "target": 9,
        "weight": 3
    }, {
        "source": 36,
        "target": 2,
        "weight": 13
    }, {
        "source": 10,
        "target": 29,
        "weight": 19
    }, {
        "source": 34,
        "target": 14,
        "weight": 27
    }, {
        "source": 38,
        "target": 8,
        "weight": 3
    }, {
        "source": 12,
        "target": 27,
        "weight": 5
    }, {
        "source": 26,
        "target": 2,
        "weight": 8
    }, {
        "source": 15,
        "target": 36,
        "weight": 2
    }, {
        "source": 19,
        "target": 33,
        "weight": 3
    }, {
        "source": 31,
        "target": 1,
        "weight": 45
    }, {
        "source": 16,
        "target": 10,
        "weight": 1
    }, {
        "source": 4,
        "target": 37,
        "weight": 5
    }, {
        "source": 33,
        "target": 40,
        "weight": 1
    }, {
        "source": 16,
        "target": 32,
        "weight": 2
    }, {
        "source": 35,
        "target": 14,
        "weight": 103
    }, {
        "source": 36,
        "target": 9,
        "weight": 47
    }, {
        "source": 0,
        "target": 18,
        "weight": 3
    }, {
        "source": 12,
        "target": 18,
        "weight": 1
    }, {
        "source": 36,
        "target": 23,
        "weight": 2
    }, {
        "source": 39,
        "target": 10,
        "weight": 3
    }, {
        "source": 31,
        "target": 14,
        "weight": 60
    }, {
        "source": 17,
        "target": 12,
        "weight": 3
    }, {
        "source": 16,
        "target": 39,
        "weight": 1
    }, {
        "source": 21,
        "target": 14,
        "weight": 1
    }, {
        "source": 8,
        "target": 13,
        "weight": 10
    }, {
        "source": 39,
        "target": 37,
        "weight": 3
    }, {
        "source": 11,
        "target": 14,
        "weight": 4
    }, {
        "source": 35,
        "target": 29,
        "weight": 20
    }, {
        "source": 9,
        "target": 18,
        "weight": 1
    }, {
        "source": 12,
        "target": 9,
        "weight": 1
    }, {
        "source": 15,
        "target": 12,
        "weight": 2
    }, {
        "source": 39,
        "target": 3,
        "weight": 12
    }, {
        "source": 0,
        "target": 15,
        "weight": 1
    }, {
        "source": 1,
        "target": 14,
        "weight": 1
    }, {
        "source": 4,
        "target": 13,
        "weight": 63
    }, {
        "source": 6,
        "target": 15,
        "weight": 1
    }, {
        "source": 19,
        "target": 21,
        "weight": 1
    }, {
        "source": 31,
        "target": 29,
        "weight": 55
    }, {
        "source": 39,
        "target": 34,
        "weight": 2
    }, {
        "source": 35,
        "target": 2,
        "weight": 1
    }, {
        "source": 15,
        "target": 21,
        "weight": 1
    }, {
        "source": 11,
        "target": 29,
        "weight": 1
    }, {
        "source": 38,
        "target": 23,
        "weight": 2
    }, {
        "source": 12,
        "target": 30,
        "weight": 39
    }, {
        "source": 6,
        "target": 6,
        "weight": 1
    }, {
        "source": 4,
        "target": 18,
        "weight": 4
    }, {
        "source": 31,
        "target": 26,
        "weight": 1
    }, {
        "source": 16,
        "target": 21,
        "weight": 1
    }, {
        "source": 19,
        "target": 0,
        "weight": 7
    }, {
        "source": 31,
        "target": 32,
        "weight": 69
    }, {
        "source": 35,
        "target": 37,
        "weight": 1
    }, {
        "source": 36,
        "target": 12,
        "weight": 1
    }, {
        "source": 15,
        "target": 18,
        "weight": 1
    }, {
        "source": 35,
        "target": 17,
        "weight": 1
    }, {
        "source": 0,
        "target": 29,
        "weight": 21
    }, {
        "source": 27,
        "target": 13,
        "weight": 25
    }, {
        "source": 4,
        "target": 25,
        "weight": 27
    }, {
        "source": 28,
        "target": 14,
        "weight": 4
    }, {
        "source": 31,
        "target": 3,
        "weight": 6
    }, {
        "source": 16,
        "target": 12,
        "weight": 8
    }, {
        "source": 6,
        "target": 19,
        "weight": 1
    }, {
        "source": 4,
        "target": 39,
        "weight": 1
    }, {
        "source": 19,
        "target": 9,
        "weight": 12
    }, {
        "source": 17,
        "target": 9,
        "weight": 11
    }, {
        "source": 22,
        "target": 22,
        "weight": 1
    }, {
        "source": 18,
        "target": 14,
        "weight": 3
    }, {
        "source": 16,
        "target": 34,
        "weight": 1
    }, {
        "source": 8,
        "target": 8,
        "weight": 1
    }, {
        "source": 23,
        "target": 13,
        "weight": 6
    }, {
        "source": 10,
        "target": 2,
        "weight": 1
    }, {
        "source": 35,
        "target": 22,
        "weight": 102
    }, {
        "source": 19,
        "target": 36,
        "weight": 1
    }, {
        "source": 36,
        "target": 17,
        "weight": 2
    }, {
        "source": 0,
        "target": 10,
        "weight": 2
    }, {
        "source": 4,
        "target": 0,
        "weight": 15
    }, {
        "source": 31,
        "target": 8,
        "weight": 42
    }, {
        "source": 5,
        "target": 5,
        "weight": 1
    }, {
        "source": 28,
        "target": 35,
        "weight": 1
    }, {
        "source": 17,
        "target": 2,
        "weight": 1
    }, {
        "source": 31,
        "target": 22,
        "weight": 22
    }, {
        "source": 9,
        "target": 14,
        "weight": 3
    }, {
        "source": 39,
        "target": 39,
        "weight": 1
    }, {
        "source": 11,
        "target": 0,
        "weight": 1
    }, {
        "source": 35,
        "target": 31,
        "weight": 1
    }, {
        "source": 10,
        "target": 23,
        "weight": 1
    }, {
        "source": 15,
        "target": 14,
        "weight": 2
    }, {
        "source": 0,
        "target": 1,
        "weight": 30
    }, {
        "source": 38,
        "target": 18,
        "weight": 1
    }, {
        "source": 27,
        "target": 27,
        "weight": 1
    }, {
        "source": 8,
        "target": 37,
        "weight": 1
    }, {
        "source": 4,
        "target": 15,
        "weight": 1
    }, {
        "source": 28,
        "target": 28,
        "weight": 1
    }, {
        "source": 30,
        "target": 30,
        "weight": 1
    }, {
        "source": 4,
        "target": 21,
        "weight": 3
    }, {
        "source": 31,
        "target": 31,
        "weight": 1
    }, {
        "source": 23,
        "target": 37,
        "weight": 1
    }, {
        "source": 21,
        "target": 21,
        "weight": 1
    }, {
        "source": 39,
        "target": 27,
        "weight": 9
    }, {
        "source": 31,
        "target": 37,
        "weight": 4
    }, {
        "source": 11,
        "target": 35,
        "weight": 1
    }, {
        "source": 23,
        "target": 3,
        "weight": 1
    }, {
        "source": 35,
        "target": 4,
        "weight": 1
    }, {
        "source": 14,
        "target": 22,
        "weight": 1
    }, {
        "source": 12,
        "target": 2,
        "weight": 1
    }, {
        "source": 15,
        "target": 23,
        "weight": 6
    }, {
        "source": 11,
        "target": 31,
        "weight": 1
    }, {
        "source": 38,
        "target": 21,
        "weight": 1
    }, {
        "source": 1,
        "target": 5,
        "weight": 143
    }, {
        "source": 2,
        "target": 2,
        "weight": 1
    }, {
        "source": 6,
        "target": 4,
        "weight": 1
    }, {
        "source": 31,
        "target": 4,
        "weight": 9
    }, {
        "source": 3,
        "target": 33,
        "weight": 4
    }, {
        "source": 19,
        "target": 2,
        "weight": 1
    }, {
        "source": 31,
        "target": 34,
        "weight": 2
    }, {
        "source": 35,
        "target": 39,
        "weight": 1
    }, {
        "source": 18,
        "target": 21,
        "weight": 1
    }, {
        "source": 36,
        "target": 32,
        "weight": 5
    }, {
        "source": 37,
        "target": 37,
        "weight": 1
    }, {
        "source": 35,
        "target": 13,
        "weight": 2
    }, {
        "source": 36,
        "target": 14,
        "weight": 3
    }, {
        "source": 35,
        "target": 19,
        "weight": 1
    }, {
        "source": 12,
        "target": 23,
        "weight": 3
    }, {
        "source": 36,
        "target": 20,
        "weight": 118
    }, {
        "source": 1,
        "target": 30,
        "weight": 1
    }, {
        "source": 39,
        "target": 9,
        "weight": 1
    }, {
        "source": 4,
        "target": 27,
        "weight": 51
    }, {
        "source": 19,
        "target": 37,
        "weight": 1
    }, {
        "source": 16,
        "target": 16,
        "weight": 1
    }, {
        "source": 27,
        "target": 37,
        "weight": 1
    }, {
        "source": 16,
        "target": 14,
        "weight": 26
    }, {
        "source": 6,
        "target": 17,
        "weight": 1
    }, {
        "source": 4,
        "target": 33,
        "weight": 13
    }, {
        "source": 9,
        "target": 33,
        "weight": 5
    }, {
        "source": 16,
        "target": 36,
        "weight": 1
    }, {
        "source": 17,
        "target": 33,
        "weight": 2
    }, {
        "source": 0,
        "target": 22,
        "weight": 25
    }, {
        "source": 12,
        "target": 14,
        "weight": 3
    }, {
        "source": 15,
        "target": 3,
        "weight": 5
    }, {
        "source": 0,
        "target": 12,
        "weight": 8
    }, {
        "source": 4,
        "target": 2,
        "weight": 1
    }, {
        "source": 31,
        "target": 10,
        "weight": 25
    }, {
        "source": 19,
        "target": 16,
        "weight": 1
    }, {
        "source": 31,
        "target": 16,
        "weight": 51
    }, {
        "source": 33,
        "target": 37,
        "weight": 1
    }, {
        "source": 40,
        "target": 40,
        "weight": 1
    }, {
        "source": 10,
        "target": 33,
        "weight": 2
    }, {
        "source": 34,
        "target": 34,
        "weight": 1
    }, {
        "source": 17,
        "target": 26,
        "weight": 7
    }, {
        "source": 38,
        "target": 36,
        "weight": 1
    }, {
        "source": 8,
        "target": 23,
        "weight": 2
    }, {
        "source": 39,
        "target": 33,
        "weight": 2
    }, {
        "source": 11,
        "target": 2,
        "weight": 1
    }, {
        "source": 35,
        "target": 1,
        "weight": 1
    }, {
        "source": 12,
        "target": 5,
        "weight": 18
    }, {
        "source": 36,
        "target": 26,
        "weight": 1
    }, {
        "source": 15,
        "target": 8,
        "weight": 10
    }, {
        "source": 0,
        "target": 3,
        "weight": 1
    }, {
        "source": 38,
        "target": 16,
        "weight": 1
    }, {
        "source": 4,
        "target": 9,
        "weight": 3
    }, {
        "source": 2,
        "target": 9,
        "weight": 1
    }, {
        "source": 4,
        "target": 23,
        "weight": 16
    }, {
        "source": 31,
        "target": 25,
        "weight": 27
    }, {
        "source": 16,
        "target": 18,
        "weight": 1
    }, {
        "source": 10,
        "target": 40,
        "weight": 1
    }, {
        "source": 31,
        "target": 39,
        "weight": 1
    }, {
        "source": 11,
        "target": 37,
        "weight": 1
    }, {
        "source": 35,
        "target": 32,
        "weight": 1
    }, {
        "source": 34,
        "target": 23,
        "weight": 2
    }, {
        "source": 15,
        "target": 17,
        "weight": 1
    }, {
        "source": 11,
        "target": 17,
        "weight": 1
    }, {
        "source": 26,
        "target": 27,
        "weight": 9
    }, {
        "source": 0,
        "target": 26,
        "weight": 1
    }, {
        "source": 24,
        "target": 7,
        "weight": 27
    }, {
        "source": 12,
        "target": 26,
        "weight": 1
    }, {
        "source": 28,
        "target": 21,
        "weight": 1
    }, {
        "source": 14,
        "target": 32,
        "weight": 1
    }, {
        "source": 15,
        "target": 37,
        "weight": 1
    }]
}